puma_iar/__init__.py
puma_iar/period.py
puma_iar/single_pulses.py
puma_iar-0.2.dist-info/METADATA
puma_iar-0.2.dist-info/WHEEL
puma_iar-0.2.dist-info/top_level.txt
puma_iar-0.2.dist-info/RECORD
