Metadata-Version: 2.1
Name: puma-iar
Version: 0.2
Summary: functions for PuMA project
Home-page: UNKNOWN
Author: Carolina Negrelli
Author-email: caro.negrelli@gmail.com
License: UNKNOWN
Platform: UNKNOWN
